{
  "_fv": 21,
  "_type": "food",
  "definition": {
    "renderType": 0,
    "texture": "chococookie",
    "customModelName": "Normal",
    "name": "Choco Chip Cookie",
    "rarity": "UNCOMMON",
    "specialInfo": [
      "A chocolate chip cookie. Looks tasty."
    ],
    "creativeTab": {
      "value": "CUSTOM:AMFoodMod"
    },
    "stackSize": 64,
    "nutritionalValue": 4,
    "saturation": 0.5,
    "eatingSpeed": 30,
    "resultItem": {
      "value": ""
    },
    "forDogs": false,
    "isAlwaysEdible": false,
    "animation": "eat",
    "hasGlow": false
  }
}