{
  "_fv": 17,
  "_type": "food",
  "definition": {
    "renderType": 0,
    "texture": "glowstone_syrup",
    "customModelName": "Normal",
    "name": "Glowstone Syrup",
    "rarity": "RARE",
    "specialInfo": [
      "It's so bright! But i hope it's drinkable."
    ],
    "creativeTab": {
      "value": "CUSTOM:AMFoodMod"
    },
    "stackSize": 16,
    "nutritionalValue": 3,
    "saturation": 0.4,
    "eatingSpeed": 35,
    "resultItem": {
      "value": ""
    },
    "forDogs": false,
    "isAlwaysEdible": true,
    "animation": "drink",
    "hasGlow": true,
    "onEaten": {
      "name": "GlowstoneSyrupFoodEaten"
    }
  }
}